MANIFEST.in
setup.py
build_big_data/__init__.py
build_big_data/main.py
build_big_data/models.py
build_big_data/utils.py
geo_squizzy.egg-info/PKG-INFO
geo_squizzy.egg-info/SOURCES.txt
geo_squizzy.egg-info/dependency_links.txt
geo_squizzy.egg-info/top_level.txt
geosquizzy/__init__.py
geosquizzy/classes.py
geosquizzy/geosquizzy.py
geosquizzy/utils.py
geosquizzy/fsm/__init__.py
geosquizzy/fsm/commands.py
geosquizzy/fsm/data.py
geosquizzy/fsm/economize.py
geosquizzy/fsm/fsm.py
geosquizzy/fsm/selection.py
geosquizzy/fsm/states.py
geosquizzy/fsm/utils.py
geosquizzy/structure/__init__.py
geosquizzy/structure/bark.py
geosquizzy/structure/geojsonTEMP.py
geosquizzy/structure/outcome.py
geosquizzy/structure/structure.py
geosquizzy/structure/utils.py
geosquizzy/validation/__init__.py
geosquizzy/validation/exceptions.py
geosquizzy/validation/messages.py
geosquizzy/validation/validation.py
tests/__init__.py
tests/getdata.py