Metadata-Version: 1.0
Name: geo-squizzy
Version: 0.2.0
Summary: GeoJSON-unknown-documents-model-creation
Home-page: https://github.com/LowerSilesians/geo-squizzy
Author: Igor Miazek, Jakub Miazek
Author-email: t-32@o2.pl, the@grillazz.com
License: MIT
Platform: UNKNOWN
